odoo9_addon_l10n_es_account_fiscal_year_closing-9.0.1.0.0.99.dev4-py2.7-nspkg.pth
odoo9_addon_l10n_es_account_fiscal_year_closing-9.0.1.0.0.99.dev4.dist-info/DESCRIPTION.rst
odoo9_addon_l10n_es_account_fiscal_year_closing-9.0.1.0.0.99.dev4.dist-info/METADATA
odoo9_addon_l10n_es_account_fiscal_year_closing-9.0.1.0.0.99.dev4.dist-info/RECORD
odoo9_addon_l10n_es_account_fiscal_year_closing-9.0.1.0.0.99.dev4.dist-info/WHEEL
odoo9_addon_l10n_es_account_fiscal_year_closing-9.0.1.0.0.99.dev4.dist-info/metadata.json
odoo9_addon_l10n_es_account_fiscal_year_closing-9.0.1.0.0.99.dev4.dist-info/namespace_packages.txt
odoo9_addon_l10n_es_account_fiscal_year_closing-9.0.1.0.0.99.dev4.dist-info/top_level.txt
odoo_addons/l10n_es_account_fiscal_year_closing/README.rst
odoo_addons/l10n_es_account_fiscal_year_closing/__init__.py
odoo_addons/l10n_es_account_fiscal_year_closing/__openerp__.py
odoo_addons/l10n_es_account_fiscal_year_closing/data/account_fiscal_year_closing_data_big.xml
odoo_addons/l10n_es_account_fiscal_year_closing/data/account_fiscal_year_closing_data_sme_ngo.xml
odoo_addons/l10n_es_account_fiscal_year_closing/i18n/ca.po
odoo_addons/l10n_es_account_fiscal_year_closing/i18n/es.po
odoo_addons/l10n_es_account_fiscal_year_closing/i18n/es_CR.po
odoo_addons/l10n_es_account_fiscal_year_closing/i18n/gl.po
odoo_addons/l10n_es_account_fiscal_year_closing/i18n/l10n_es_account_fiscal_year_closing.pot
odoo_addons/l10n_es_account_fiscal_year_closing/i18n/pt_BR.po
odoo_addons/l10n_es_account_fiscal_year_closing/i18n/sl.po
odoo_addons/l10n_es_account_fiscal_year_closing/i18n/tr.po
odoo_addons/l10n_es_account_fiscal_year_closing/static/description/icon.png
odoo_addons/l10n_es_account_fiscal_year_closing/static/description/icon.svg
